julienne/__init__.py
julienne/cmd.py
julienne/filemodel.py
julienne/nodes.py
julienne/parsers.py
julienne-0.8.2.dist-info/LICENSE
julienne-0.8.2.dist-info/METADATA
julienne-0.8.2.dist-info/WHEEL
julienne-0.8.2.dist-info/entry_points.txt
julienne-0.8.2.dist-info/top_level.txt
julienne-0.8.2.dist-info/RECORD
