Metadata-Version: 2.1
Name: julienne
Version: 0.8.2
Summary: Splits code into copies based on version numbers in comments
Home-page: https://github.com/cltrudeau/julienne
Author: Christopher Trudeau
License: MIT
Classifier: Development Status :: 3 - Alpha
Classifier: Intended Audience :: Developers
Classifier: Intended Audience :: Education
Classifier: License :: OSI Approved :: MIT License
Classifier: Programming Language :: Python :: 3.7
Classifier: Programming Language :: Python :: 3.8
Classifier: Programming Language :: Python :: 3.9
Classifier: Programming Language :: Python :: 3.10
Classifier: Programming Language :: Python :: 3.11
Classifier: Topic :: Software Development :: Code Generators
Classifier: Topic :: Software Development :: Libraries :: Python Modules
License-File: LICENSE
Requires-Dist: black ==23.1.0
Requires-Dist: isort ==5.12.0
Requires-Dist: tomli ==2.0.1
Provides-Extra: dev
Requires-Dist: build ==0.8.0 ; extra == 'dev'
Requires-Dist: coverage ==6.5.0 ; extra == 'dev'
Requires-Dist: pudb ==2022.1.2 ; extra == 'dev'
Requires-Dist: pyflakes ==2.5.0 ; extra == 'dev'
Requires-Dist: tox ==3.26.0 ; extra == 'dev'
Requires-Dist: twine ==4.0.1 ; extra == 'dev'
Requires-Dist: waelstow ==0.11.0 ; extra == 'dev'
